{"chunk_definitions":[{"chunk_id":"cd9p12730a6ua","chunk_label":"confusion matrix draw function","document_id":"B40427F","expansion_state":0,"options":{"engine":"r","include":false,"label":"confusion matrix draw function"},"row":51,"row_count":1,"visible":true},{"chunk_id":"c2b27wzwzzxvt","chunk_label":"confusion matrix","document_id":"B40427F","expansion_state":0,"options":{"engine":"r","label":"predictions"},"row":229,"row_count":1,"visible":true},{"chunk_id":"cme2ssd4yaiql","chunk_label":"results rf","document_id":"71C5E79E","expansion_state":0,"options":{"engine":"r","fig.asp":1.500000000000000,"label":"results rf"},"row":617,"row_count":1,"visible":true}],"doc_write_time":1606767695}